efold/__init__.py
efold/cli.py
efold/config.py
efold/api/__init__.py
efold/api/run.py
efold/core/__init__.py
efold/core/batch.py
efold/core/callbacks.py
efold/core/dataloader.py
efold/core/datamodule.py
efold/core/dataset.py
efold/core/datatype.py
efold/core/embeddings.py
efold/core/loader.py
efold/core/logger.py
efold/core/metrics.py
efold/core/model.py
efold/core/path.py
efold/core/postprocess.py
efold/core/sampler.py
efold/core/util.py
efold/core/visualisation.py
efold/models/__init__.py
efold/models/cnn.py
efold/models/efold.py
efold/models/factory.py
efold/models/ribonanza.py
efold/models/transformer.py
efold/models/unet.py
efold/resources/efold_weights.pt
efold/util/__init__.py
efold/util/format_conversion.py
efold-0.1.2.dist-info/LICENSE
efold-0.1.2.dist-info/METADATA
efold-0.1.2.dist-info/WHEEL
efold-0.1.2.dist-info/entry_points.txt
efold-0.1.2.dist-info/top_level.txt
efold-0.1.2.dist-info/RECORD
