Metadata-Version: 2.1
Name: efold
Version: 0.1.2
Summary: A library to build our DMS signal and RNAstructure prediction models.
Author-email: Yves Martin <yves@martin.yt>, Alberic de Lajarte <albericlajarte@gmail.com>
Classifier: Development Status :: 3 - Alpha
Classifier: Intended Audience :: Developers
Classifier: Programming Language :: Python :: 3.10
Requires-Python: >=3.10
License-File: LICENSE
Requires-Dist: pandas >=1.5.2
Requires-Dist: matplotlib >=3.6.2
Requires-Dist: plotly >=5.11.0
Requires-Dist: torch >=1.13.1
Requires-Dist: pytorch-lightning >=1.9.4
Requires-Dist: lightning >=1.9.4
Requires-Dist: torcheval >=0.0.6
Requires-Dist: tensorboard >=2.11.2
Requires-Dist: wandb
Requires-Dist: rouskinhf
Requires-Dist: einops
Requires-Dist: huggingface-hub
Requires-Dist: scikit-learn
Requires-Dist: envbash
Requires-Dist: click
